valimp/__init__.py
valimp/_version.py
valimp/valimp.py
valimp-0.4.dist-info/licenses/LICENSE.txt
valimp-0.4.dist-info/METADATA
valimp-0.4.dist-info/WHEEL
valimp-0.4.dist-info/top_level.txt
valimp-0.4.dist-info/RECORD
