Metadata-Version: 2.4
Name: valimp
Version: 0.4
Summary: Validate and parse function inputs
Author: Marcus Read
Author-email: marcusaread.prog@proton.me
License-Expression: MIT
Project-URL: homepage, https://github.com/maread99/valimp
Project-URL: documentation, https://github.com/maread99/valimp
Project-URL: Issue Tracker, https://github.com/maread99/valimp/issues
Project-URL: Source Code, https://github.com/maread99/valimp
Keywords: validation,parsing,validate,parse,coerce,input,function
Classifier: Development Status :: 4 - Beta
Classifier: Intended Audience :: Developers
Classifier: Natural Language :: English
Classifier: Operating System :: OS Independent
Classifier: Programming Language :: Python
Classifier: Programming Language :: Python :: 3
Classifier: Programming Language :: Python :: 3 :: Only
Classifier: Programming Language :: Python :: 3.9
Classifier: Programming Language :: Python :: 3.10
Classifier: Programming Language :: Python :: 3.11
Classifier: Programming Language :: Python :: 3.12
Classifier: Programming Language :: Python :: 3.13
Classifier: Programming Language :: Python :: Implementation :: CPython
Classifier: Topic :: Software Development :: Libraries :: Python Modules
Classifier: Topic :: Utilities
Requires-Python: <4,>=3.9
License-File: LICENSE.txt
Dynamic: license-file
